heroshot/__init__.py
heroshot/mkdocs.py
heroshot/sphinx.py
heroshot-0.12.0.dist-info/METADATA
heroshot-0.12.0.dist-info/WHEEL
heroshot-0.12.0.dist-info/top_level.txt
heroshot-0.12.0.dist-info/RECORD
